orcha_watchdog/__init__.py
orcha_watchdog/client.py
orcha_watchdog/constants.py
orcha_watchdog/petition.py
orcha_watchdog/watchdog.py
orcha_watchdog-0.1.5.dist-info/WHEEL
orcha_watchdog-0.1.5.dist-info/METADATA
orcha_watchdog-0.1.5.dist-info/RECORD
