Metadata-Version: 2.1
Name: orcha-watchdog
Version: 0.1.5
Summary: Orcha pluggable for SystemD Watchdog integration
License: MIT
Author: Javier Alonso
Author-email: jalonso@teldat.com
Requires-Python: >=3.7.2,<4.0.0
Classifier: License :: OSI Approved :: MIT License
Classifier: Programming Language :: Python :: 3
Classifier: Programming Language :: Python :: 3.10
Classifier: Programming Language :: Python :: 3.8
Classifier: Programming Language :: Python :: 3.9
Requires-Dist: orcha (==0.3.0-rc2)
Requires-Dist: systemd-python (>=234,<235)
